django_payments_mollie/__init__.py
django_payments_mollie/facade.py
django_payments_mollie/models.py
django_payments_mollie/provider.py
django_payments_mollie-0.0.1.dist-info/LICENSE.txt
django_payments_mollie-0.0.1.dist-info/WHEEL
django_payments_mollie-0.0.1.dist-info/METADATA
django_payments_mollie-0.0.1.dist-info/RECORD
