Metadata-Version: 2.1
Name: django-payments-mollie
Version: 0.0.1
Summary: Mollie integration for django-payments
Keywords: 
Author-email: Four Digits <info@fourdigits.nl>
Requires-Python: >=3.7
Classifier: Development Status :: 4 - Beta
Classifier: Programming Language :: Python
Classifier: Programming Language :: Python :: 3.7
Classifier: Programming Language :: Python :: 3.8
Classifier: Programming Language :: Python :: 3.9
Classifier: Programming Language :: Python :: 3.10
Classifier: Programming Language :: Python :: 3.11
Classifier: Programming Language :: Python :: Implementation :: CPython
Classifier: Programming Language :: Python :: Implementation :: PyPy
Requires-Dist: django-payments
Requires-Dist: mollie-api-python >=3.1.0
Requires-Dist: flit ; extra == "dev"
Requires-Dist: pytest ; extra == "test"
Requires-Dist: pytest-cov ; extra == "test"
Requires-Dist: pytest-django ; extra == "test"
Requires-Dist: pytest-mock ; extra == "test"
Requires-Dist: dj_database_url ; extra == "test"
Requires-Dist: factory_boy ; extra == "test"
Project-URL: Documentation, https://github.com/fourdigits/django-payments-mollie#readme
Project-URL: Issues, https://github.com/fourdigits/django-payments-mollie/issues
Project-URL: Source, https://github.com/fourdigits/django-payments-mollie
Provides-Extra: dev
Provides-Extra: test
